[
  {
    "id": "5759",
    "surah": "80",
    "ayah": "1",
    "arab": "عَبَسَ وَتَوَلّٰىٓۙ",
    "latin": "‘Abasa wa tawallā.",
    "page": "585",
    "juz": "30",
    "hizb": "59.25",
    "asbab": "1",
    "audio": "https://cdn.alquran.cloud/media/audio/ayah/ar.alafasy/5759",
    "theme": null,
    "text": "Dia (Nabi Muhammad) berwajah masam dan berpaling",
    "notes": null,
    "audio_partial": "{\"01\":\"https://cdn.equran.id/audio-partial/Abdullah-Al-Juhany/080001.mp3\",\"02\":\"https://cdn.equran.id/audio-partial/Abdul-Muhsin-Al-Qasim/080001.mp3\",\"03\":\"https://cdn.equran.id/audio-partial/Abdurrahman-as-Sudais/080001.mp3\",\"04\":\"https://cdn.equran.id/audio-partial/Ibrahim-Al-Dossari/080001.mp3\",\"05\":\"https://cdn.equran.id/audio-partial/Misyari-Rasyid-Al-Afasi/080001.mp3\",\"06\":\"https://cdn.equran.id/audio-partial/Yasser-Al-Dosari/080001.mp3\"}"
  },
  {
    "id": "5760",
    "surah": "80",
    "ayah": "2",
    "arab": "اَنْ جَاۤءَهُ الْاَعْمٰىۗ",
    "latin": "An jā'ahul-a‘mā.",
    "page": "585",
    "juz": "30",
    "hizb": "59.25",
    "asbab": "1",
    "audio": "https://cdn.alquran.cloud/media/audio/ayah/ar.alafasy/5760",
    "theme": null,
    "text": "karena seorang tunanetra (Abdullah bin Ummi Maktum) telah datang kepadanya.",
    "notes": null,
    "audio_partial": "{\"01\":\"https://cdn.equran.id/audio-partial/Abdullah-Al-Juhany/080002.mp3\",\"02\":\"https://cdn.equran.id/audio-partial/Abdul-Muhsin-Al-Qasim/080002.mp3\",\"03\":\"https://cdn.equran.id/audio-partial/Abdurrahman-as-Sudais/080002.mp3\",\"04\":\"https://cdn.equran.id/audio-partial/Ibrahim-Al-Dossari/080002.mp3\",\"05\":\"https://cdn.equran.id/audio-partial/Misyari-Rasyid-Al-Afasi/080002.mp3\",\"06\":\"https://cdn.equran.id/audio-partial/Yasser-Al-Dosari/080002.mp3\"}"
  },
  {
    "id": "5761",
    "surah": "80",
    "ayah": "3",
    "arab": "وَمَا يُدْرِيْكَ لَعَلَّهٗ يَزَّكّٰىٓۙ",
    "latin": "Wa mā yudrīka la‘allahū yazzakkā.",
    "page": "585",
    "juz": "30",
    "hizb": "59.25",
    "asbab": "1",
    "audio": "https://cdn.alquran.cloud/media/audio/ayah/ar.alafasy/5761",
    "theme": null,
    "text": "Tahukah engkau (Nabi Muhammad) boleh jadi dia ingin menyucikan dirinya (dari dosa)",
    "notes": null,
    "audio_partial": "{\"01\":\"https://cdn.equran.id/audio-partial/Abdullah-Al-Juhany/080003.mp3\",\"02\":\"https://cdn.equran.id/audio-partial/Abdul-Muhsin-Al-Qasim/080003.mp3\",\"03\":\"https://cdn.equran.id/audio-partial/Abdurrahman-as-Sudais/080003.mp3\",\"04\":\"https://cdn.equran.id/audio-partial/Ibrahim-Al-Dossari/080003.mp3\",\"05\":\"https://cdn.equran.id/audio-partial/Misyari-Rasyid-Al-Afasi/080003.mp3\",\"06\":\"https://cdn.equran.id/audio-partial/Yasser-Al-Dosari/080003.mp3\"}"
  },
  {
    "id": "5762",
    "surah": "80",
    "ayah": "4",
    "arab": "اَوْ يَذَّكَّرُ فَتَنْفَعَهُ الذِّكْرٰىۗ",
    "latin": "Au yażżakkaru fatanfa‘ahuż-żikrā.",
    "page": "585",
    "juz": "30",
    "hizb": "59.25",
    "asbab": "1",
    "audio": "https://cdn.alquran.cloud/media/audio/ayah/ar.alafasy/5762",
    "theme": null,
    "text": "atau dia (ingin) mendapatkan pengajaran sehingga pengajaran itu bermanfaat baginya?",
    "notes": null,
    "audio_partial": "{\"01\":\"https://cdn.equran.id/audio-partial/Abdullah-Al-Juhany/080004.mp3\",\"02\":\"https://cdn.equran.id/audio-partial/Abdul-Muhsin-Al-Qasim/080004.mp3\",\"03\":\"https://cdn.equran.id/audio-partial/Abdurrahman-as-Sudais/080004.mp3\",\"04\":\"https://cdn.equran.id/audio-partial/Ibrahim-Al-Dossari/080004.mp3\",\"05\":\"https://cdn.equran.id/audio-partial/Misyari-Rasyid-Al-Afasi/080004.mp3\",\"06\":\"https://cdn.equran.id/audio-partial/Yasser-Al-Dosari/080004.mp3\"}"
  },
  {
    "id": "5763",
    "surah": "80",
    "ayah": "5",
    "arab": "اَمَّا مَنِ اسْتَغْنٰىۙ",
    "latin": "Ammā manistagnā.",
    "page": "585",
    "juz": "30",
    "hizb": "59.25",
    "asbab": "1",
    "audio": "https://cdn.alquran.cloud/media/audio/ayah/ar.alafasy/5763",
    "theme": null,
    "text": "Adapun orang yang merasa dirinya serba cukup (para pembesar Quraisy),",
    "notes": null,
    "audio_partial": "{\"01\":\"https://cdn.equran.id/audio-partial/Abdullah-Al-Juhany/080005.mp3\",\"02\":\"https://cdn.equran.id/audio-partial/Abdul-Muhsin-Al-Qasim/080005.mp3\",\"03\":\"https://cdn.equran.id/audio-partial/Abdurrahman-as-Sudais/080005.mp3\",\"04\":\"https://cdn.equran.id/audio-partial/Ibrahim-Al-Dossari/080005.mp3\",\"05\":\"https://cdn.equran.id/audio-partial/Misyari-Rasyid-Al-Afasi/080005.mp3\",\"06\":\"https://cdn.equran.id/audio-partial/Yasser-Al-Dosari/080005.mp3\"}"
  },
  {
    "id": "5764",
    "surah": "80",
    "ayah": "6",
    "arab": "فَاَنْتَ لَهٗ تَصَدّٰىۗ",
    "latin": "Fa anta lahū taṣaddā.",
    "page": "585",
    "juz": "30",
    "hizb": "59.25",
    "asbab": "1",
    "audio": "https://cdn.alquran.cloud/media/audio/ayah/ar.alafasy/5764",
    "theme": null,
    "text": "engkau (Nabi Muhammad) memberi perhatian kepadanya.",
    "notes": null,
    "audio_partial": "{\"01\":\"https://cdn.equran.id/audio-partial/Abdullah-Al-Juhany/080006.mp3\",\"02\":\"https://cdn.equran.id/audio-partial/Abdul-Muhsin-Al-Qasim/080006.mp3\",\"03\":\"https://cdn.equran.id/audio-partial/Abdurrahman-as-Sudais/080006.mp3\",\"04\":\"https://cdn.equran.id/audio-partial/Ibrahim-Al-Dossari/080006.mp3\",\"05\":\"https://cdn.equran.id/audio-partial/Misyari-Rasyid-Al-Afasi/080006.mp3\",\"06\":\"https://cdn.equran.id/audio-partial/Yasser-Al-Dosari/080006.mp3\"}"
  },
  {
    "id": "5765",
    "surah": "80",
    "ayah": "7",
    "arab": "وَمَا عَلَيْكَ اَلَّا يَزَّكّٰىۗ",
    "latin": "Wa mā ‘alaika allā yazzakkā.",
    "page": "585",
    "juz": "30",
    "hizb": "59.25",
    "asbab": "1",
    "audio": "https://cdn.alquran.cloud/media/audio/ayah/ar.alafasy/5765",
    "theme": null,
    "text": "Padahal, tidak ada (cela) atasmu kalau dia tidak menyucikan diri (beriman).",
    "notes": null,
    "audio_partial": "{\"01\":\"https://cdn.equran.id/audio-partial/Abdullah-Al-Juhany/080007.mp3\",\"02\":\"https://cdn.equran.id/audio-partial/Abdul-Muhsin-Al-Qasim/080007.mp3\",\"03\":\"https://cdn.equran.id/audio-partial/Abdurrahman-as-Sudais/080007.mp3\",\"04\":\"https://cdn.equran.id/audio-partial/Ibrahim-Al-Dossari/080007.mp3\",\"05\":\"https://cdn.equran.id/audio-partial/Misyari-Rasyid-Al-Afasi/080007.mp3\",\"06\":\"https://cdn.equran.id/audio-partial/Yasser-Al-Dosari/080007.mp3\"}"
  },
  {
    "id": "5766",
    "surah": "80",
    "ayah": "8",
    "arab": "وَاَمَّا مَنْ جَاۤءَكَ يَسْعٰىۙ",
    "latin": "Wa ammā man jā'aka yas‘ā.",
    "page": "585",
    "juz": "30",
    "hizb": "59.25",
    "asbab": "1",
    "audio": "https://cdn.alquran.cloud/media/audio/ayah/ar.alafasy/5766",
    "theme": null,
    "text": "Adapun orang yang datang kepadamu dengan bersegera (untuk mendapatkan pengajaran),",
    "notes": null,
    "audio_partial": "{\"01\":\"https://cdn.equran.id/audio-partial/Abdullah-Al-Juhany/080008.mp3\",\"02\":\"https://cdn.equran.id/audio-partial/Abdul-Muhsin-Al-Qasim/080008.mp3\",\"03\":\"https://cdn.equran.id/audio-partial/Abdurrahman-as-Sudais/080008.mp3\",\"04\":\"https://cdn.equran.id/audio-partial/Ibrahim-Al-Dossari/080008.mp3\",\"05\":\"https://cdn.equran.id/audio-partial/Misyari-Rasyid-Al-Afasi/080008.mp3\",\"06\":\"https://cdn.equran.id/audio-partial/Yasser-Al-Dosari/080008.mp3\"}"
  },
  {
    "id": "5767",
    "surah": "80",
    "ayah": "9",
    "arab": "وَهُوَ يَخْشٰىۙ",
    "latin": "Wa huwa yakhsyā.",
    "page": "585",
    "juz": "30",
    "hizb": "59.25",
    "asbab": "1",
    "audio": "https://cdn.alquran.cloud/media/audio/ayah/ar.alafasy/5767",
    "theme": null,
    "text": "sedangkan dia takut (kepada Allah),",
    "notes": null,
    "audio_partial": "{\"01\":\"https://cdn.equran.id/audio-partial/Abdullah-Al-Juhany/080009.mp3\",\"02\":\"https://cdn.equran.id/audio-partial/Abdul-Muhsin-Al-Qasim/080009.mp3\",\"03\":\"https://cdn.equran.id/audio-partial/Abdurrahman-as-Sudais/080009.mp3\",\"04\":\"https://cdn.equran.id/audio-partial/Ibrahim-Al-Dossari/080009.mp3\",\"05\":\"https://cdn.equran.id/audio-partial/Misyari-Rasyid-Al-Afasi/080009.mp3\",\"06\":\"https://cdn.equran.id/audio-partial/Yasser-Al-Dosari/080009.mp3\"}"
  },
  {
    "id": "5768",
    "surah": "80",
    "ayah": "10",
    "arab": "فَاَنْتَ عَنْهُ تَلَهّٰىۚ",
    "latin": "Fa anta ‘anhu talahhā.",
    "page": "585",
    "juz": "30",
    "hizb": "59.25",
    "asbab": "1",
    "audio": "https://cdn.alquran.cloud/media/audio/ayah/ar.alafasy/5768",
    "theme": null,
    "text": "malah engkau (Nabi Muhammad) abaikan.",
    "notes": null,
    "audio_partial": "{\"01\":\"https://cdn.equran.id/audio-partial/Abdullah-Al-Juhany/080010.mp3\",\"02\":\"https://cdn.equran.id/audio-partial/Abdul-Muhsin-Al-Qasim/080010.mp3\",\"03\":\"https://cdn.equran.id/audio-partial/Abdurrahman-as-Sudais/080010.mp3\",\"04\":\"https://cdn.equran.id/audio-partial/Ibrahim-Al-Dossari/080010.mp3\",\"05\":\"https://cdn.equran.id/audio-partial/Misyari-Rasyid-Al-Afasi/080010.mp3\",\"06\":\"https://cdn.equran.id/audio-partial/Yasser-Al-Dosari/080010.mp3\"}"
  },
  {
    "id": "5769",
    "surah": "80",
    "ayah": "11",
    "arab": "كَلَّآ اِنَّهَا تَذْكِرَةٌ ۚ",
    "latin": "Kallā innahā tażkirah(tun).",
    "page": "585",
    "juz": "30",
    "hizb": "59.25",
    "asbab": "0",
    "audio": "https://cdn.alquran.cloud/media/audio/ayah/ar.alafasy/5769",
    "theme": null,
    "text": "Sekali-kali jangan (begitu)! Sesungguhnya (ajaran Allah) itu merupakan peringatan.",
    "notes": null,
    "audio_partial": "{\"01\":\"https://cdn.equran.id/audio-partial/Abdullah-Al-Juhany/080011.mp3\",\"02\":\"https://cdn.equran.id/audio-partial/Abdul-Muhsin-Al-Qasim/080011.mp3\",\"03\":\"https://cdn.equran.id/audio-partial/Abdurrahman-as-Sudais/080011.mp3\",\"04\":\"https://cdn.equran.id/audio-partial/Ibrahim-Al-Dossari/080011.mp3\",\"05\":\"https://cdn.equran.id/audio-partial/Misyari-Rasyid-Al-Afasi/080011.mp3\",\"06\":\"https://cdn.equran.id/audio-partial/Yasser-Al-Dosari/080011.mp3\"}"
  },
  {
    "id": "5770",
    "surah": "80",
    "ayah": "12",
    "arab": "فَمَنْ شَاۤءَ ذَكَرَهٗ ۘ",
    "latin": "Faman syā'a żakarah(ū).",
    "page": "585",
    "juz": "30",
    "hizb": "59.25",
    "asbab": "0",
    "audio": "https://cdn.alquran.cloud/media/audio/ayah/ar.alafasy/5770",
    "theme": null,
    "text": "Siapa yang menghendaki tentulah akan memperhatikannya",
    "notes": null,
    "audio_partial": "{\"01\":\"https://cdn.equran.id/audio-partial/Abdullah-Al-Juhany/080012.mp3\",\"02\":\"https://cdn.equran.id/audio-partial/Abdul-Muhsin-Al-Qasim/080012.mp3\",\"03\":\"https://cdn.equran.id/audio-partial/Abdurrahman-as-Sudais/080012.mp3\",\"04\":\"https://cdn.equran.id/audio-partial/Ibrahim-Al-Dossari/080012.mp3\",\"05\":\"https://cdn.equran.id/audio-partial/Misyari-Rasyid-Al-Afasi/080012.mp3\",\"06\":\"https://cdn.equran.id/audio-partial/Yasser-Al-Dosari/080012.mp3\"}"
  },
  {
    "id": "5771",
    "surah": "80",
    "ayah": "13",
    "arab": "فِيْ صُحُفٍ مُّكَرَّمَةٍۙ",
    "latin": "Fī ṣuḥufim mukarrmah(tin).",
    "page": "585",
    "juz": "30",
    "hizb": "59.25",
    "asbab": "0",
    "audio": "https://cdn.alquran.cloud/media/audio/ayah/ar.alafasy/5771",
    "theme": null,
    "text": "di dalam suhuf yang dimuliakan (di sisi Allah),",
    "notes": null,
    "audio_partial": "{\"01\":\"https://cdn.equran.id/audio-partial/Abdullah-Al-Juhany/080013.mp3\",\"02\":\"https://cdn.equran.id/audio-partial/Abdul-Muhsin-Al-Qasim/080013.mp3\",\"03\":\"https://cdn.equran.id/audio-partial/Abdurrahman-as-Sudais/080013.mp3\",\"04\":\"https://cdn.equran.id/audio-partial/Ibrahim-Al-Dossari/080013.mp3\",\"05\":\"https://cdn.equran.id/audio-partial/Misyari-Rasyid-Al-Afasi/080013.mp3\",\"06\":\"https://cdn.equran.id/audio-partial/Yasser-Al-Dosari/080013.mp3\"}"
  },
  {
    "id": "5772",
    "surah": "80",
    "ayah": "14",
    "arab": "مَّرْفُوْعَةٍ مُّطَهَّرَةٍ ۢ ۙ",
    "latin": "Marfū‘atim muṭahharah(tin).",
    "page": "585",
    "juz": "30",
    "hizb": "59.25",
    "asbab": "0",
    "audio": "https://cdn.alquran.cloud/media/audio/ayah/ar.alafasy/5772",
    "theme": null,
    "text": "yang ditinggikan (kedudukannya) lagi disucikan",
    "notes": null,
    "audio_partial": "{\"01\":\"https://cdn.equran.id/audio-partial/Abdullah-Al-Juhany/080014.mp3\",\"02\":\"https://cdn.equran.id/audio-partial/Abdul-Muhsin-Al-Qasim/080014.mp3\",\"03\":\"https://cdn.equran.id/audio-partial/Abdurrahman-as-Sudais/080014.mp3\",\"04\":\"https://cdn.equran.id/audio-partial/Ibrahim-Al-Dossari/080014.mp3\",\"05\":\"https://cdn.equran.id/audio-partial/Misyari-Rasyid-Al-Afasi/080014.mp3\",\"06\":\"https://cdn.equran.id/audio-partial/Yasser-Al-Dosari/080014.mp3\"}"
  },
  {
    "id": "5773",
    "surah": "80",
    "ayah": "15",
    "arab": "بِاَيْدِيْ سَفَرَةٍۙ",
    "latin": "Bi'aidī safarah(tin).",
    "page": "585",
    "juz": "30",
    "hizb": "59.25",
    "asbab": "0",
    "audio": "https://cdn.alquran.cloud/media/audio/ayah/ar.alafasy/5773",
    "theme": null,
    "text": "di tangan para utusan (malaikat)",
    "notes": null,
    "audio_partial": "{\"01\":\"https://cdn.equran.id/audio-partial/Abdullah-Al-Juhany/080015.mp3\",\"02\":\"https://cdn.equran.id/audio-partial/Abdul-Muhsin-Al-Qasim/080015.mp3\",\"03\":\"https://cdn.equran.id/audio-partial/Abdurrahman-as-Sudais/080015.mp3\",\"04\":\"https://cdn.equran.id/audio-partial/Ibrahim-Al-Dossari/080015.mp3\",\"05\":\"https://cdn.equran.id/audio-partial/Misyari-Rasyid-Al-Afasi/080015.mp3\",\"06\":\"https://cdn.equran.id/audio-partial/Yasser-Al-Dosari/080015.mp3\"}"
  },
  {
    "id": "5774",
    "surah": "80",
    "ayah": "16",
    "arab": "كِرَامٍۢ بَرَرَةٍۗ",
    "latin": "Kirāmim bararah(tin).",
    "page": "585",
    "juz": "30",
    "hizb": "59.25",
    "asbab": "0",
    "audio": "https://cdn.alquran.cloud/media/audio/ayah/ar.alafasy/5774",
    "theme": null,
    "text": "yang mulia lagi berbudi.",
    "notes": null,
    "audio_partial": "{\"01\":\"https://cdn.equran.id/audio-partial/Abdullah-Al-Juhany/080016.mp3\",\"02\":\"https://cdn.equran.id/audio-partial/Abdul-Muhsin-Al-Qasim/080016.mp3\",\"03\":\"https://cdn.equran.id/audio-partial/Abdurrahman-as-Sudais/080016.mp3\",\"04\":\"https://cdn.equran.id/audio-partial/Ibrahim-Al-Dossari/080016.mp3\",\"05\":\"https://cdn.equran.id/audio-partial/Misyari-Rasyid-Al-Afasi/080016.mp3\",\"06\":\"https://cdn.equran.id/audio-partial/Yasser-Al-Dosari/080016.mp3\"}"
  },
  {
    "id": "5775",
    "surah": "80",
    "ayah": "17",
    "arab": "قُتِلَ الْاِنْسَانُ مَآ اَكْفَرَهٗۗ",
    "latin": "Qutilal-insānu mā akfarah(ū).",
    "page": "585",
    "juz": "30",
    "hizb": "59.25",
    "asbab": "0",
    "audio": "https://cdn.alquran.cloud/media/audio/ayah/ar.alafasy/5775",
    "theme": null,
    "text": "Celakalah manusia! Alangkah kufur dia!",
    "notes": null,
    "audio_partial": "{\"01\":\"https://cdn.equran.id/audio-partial/Abdullah-Al-Juhany/080017.mp3\",\"02\":\"https://cdn.equran.id/audio-partial/Abdul-Muhsin-Al-Qasim/080017.mp3\",\"03\":\"https://cdn.equran.id/audio-partial/Abdurrahman-as-Sudais/080017.mp3\",\"04\":\"https://cdn.equran.id/audio-partial/Ibrahim-Al-Dossari/080017.mp3\",\"05\":\"https://cdn.equran.id/audio-partial/Misyari-Rasyid-Al-Afasi/080017.mp3\",\"06\":\"https://cdn.equran.id/audio-partial/Yasser-Al-Dosari/080017.mp3\"}"
  },
  {
    "id": "5776",
    "surah": "80",
    "ayah": "18",
    "arab": "مِنْ اَيِّ شَيْءٍ خَلَقَهٗۗ",
    "latin": "Min ayyi syai'in khalaqah(ū).",
    "page": "585",
    "juz": "30",
    "hizb": "59.25",
    "asbab": "0",
    "audio": "https://cdn.alquran.cloud/media/audio/ayah/ar.alafasy/5776",
    "theme": null,
    "text": "Dari apakah Dia menciptakannya?",
    "notes": null,
    "audio_partial": "{\"01\":\"https://cdn.equran.id/audio-partial/Abdullah-Al-Juhany/080018.mp3\",\"02\":\"https://cdn.equran.id/audio-partial/Abdul-Muhsin-Al-Qasim/080018.mp3\",\"03\":\"https://cdn.equran.id/audio-partial/Abdurrahman-as-Sudais/080018.mp3\",\"04\":\"https://cdn.equran.id/audio-partial/Ibrahim-Al-Dossari/080018.mp3\",\"05\":\"https://cdn.equran.id/audio-partial/Misyari-Rasyid-Al-Afasi/080018.mp3\",\"06\":\"https://cdn.equran.id/audio-partial/Yasser-Al-Dosari/080018.mp3\"}"
  },
  {
    "id": "5777",
    "surah": "80",
    "ayah": "19",
    "arab": "مِنْ نُّطْفَةٍۗ خَلَقَهٗ فَقَدَّرَهٗۗ",
    "latin": "Min nuṭfah(tin), khalaqahū fa qaddarah(ū).",
    "page": "585",
    "juz": "30",
    "hizb": "59.25",
    "asbab": "0",
    "audio": "https://cdn.alquran.cloud/media/audio/ayah/ar.alafasy/5777",
    "theme": null,
    "text": "Dia menciptakannya dari setetes mani, lalu menentukan (takdir)-nya.",
    "notes": null,
    "audio_partial": "{\"01\":\"https://cdn.equran.id/audio-partial/Abdullah-Al-Juhany/080019.mp3\",\"02\":\"https://cdn.equran.id/audio-partial/Abdul-Muhsin-Al-Qasim/080019.mp3\",\"03\":\"https://cdn.equran.id/audio-partial/Abdurrahman-as-Sudais/080019.mp3\",\"04\":\"https://cdn.equran.id/audio-partial/Ibrahim-Al-Dossari/080019.mp3\",\"05\":\"https://cdn.equran.id/audio-partial/Misyari-Rasyid-Al-Afasi/080019.mp3\",\"06\":\"https://cdn.equran.id/audio-partial/Yasser-Al-Dosari/080019.mp3\"}"
  },
  {
    "id": "5778",
    "surah": "80",
    "ayah": "20",
    "arab": "ثُمَّ السَّبِيْلَ يَسَّرَهٗۙ",
    "latin": "Ṡummas-sabīla yassarah(ū).",
    "page": "585",
    "juz": "30",
    "hizb": "59.25",
    "asbab": "0",
    "audio": "https://cdn.alquran.cloud/media/audio/ayah/ar.alafasy/5778",
    "theme": null,
    "text": "Kemudian, jalannya Dia mudahkan.746)",
    "notes": "746) Maksudnya adalah memudahkan kelahirannya atau mempermudah baginya untuk menempuh jalan yang benar atau jalan yang sesat.",
    "audio_partial": "{\"01\":\"https://cdn.equran.id/audio-partial/Abdullah-Al-Juhany/080020.mp3\",\"02\":\"https://cdn.equran.id/audio-partial/Abdul-Muhsin-Al-Qasim/080020.mp3\",\"03\":\"https://cdn.equran.id/audio-partial/Abdurrahman-as-Sudais/080020.mp3\",\"04\":\"https://cdn.equran.id/audio-partial/Ibrahim-Al-Dossari/080020.mp3\",\"05\":\"https://cdn.equran.id/audio-partial/Misyari-Rasyid-Al-Afasi/080020.mp3\",\"06\":\"https://cdn.equran.id/audio-partial/Yasser-Al-Dosari/080020.mp3\"}"
  },
  {
    "id": "5779",
    "surah": "80",
    "ayah": "21",
    "arab": "ثُمَّ اَمَاتَهٗ فَاَقْبَرَهٗۙ",
    "latin": "Ṡumma amātahū fa aqbarah(ū).",
    "page": "585",
    "juz": "30",
    "hizb": "59.25",
    "asbab": "0",
    "audio": "https://cdn.alquran.cloud/media/audio/ayah/ar.alafasy/5779",
    "theme": null,
    "text": "Kemudian, Dia mematikannya lalu menguburkannya.",
    "notes": null,
    "audio_partial": "{\"01\":\"https://cdn.equran.id/audio-partial/Abdullah-Al-Juhany/080021.mp3\",\"02\":\"https://cdn.equran.id/audio-partial/Abdul-Muhsin-Al-Qasim/080021.mp3\",\"03\":\"https://cdn.equran.id/audio-partial/Abdurrahman-as-Sudais/080021.mp3\",\"04\":\"https://cdn.equran.id/audio-partial/Ibrahim-Al-Dossari/080021.mp3\",\"05\":\"https://cdn.equran.id/audio-partial/Misyari-Rasyid-Al-Afasi/080021.mp3\",\"06\":\"https://cdn.equran.id/audio-partial/Yasser-Al-Dosari/080021.mp3\"}"
  },
  {
    "id": "5780",
    "surah": "80",
    "ayah": "22",
    "arab": "ثُمَّ اِذَا شَاۤءَ اَنْشَرَهٗۗ",
    "latin": "Ṡumma iżā syā'a ansyarah(ū).",
    "page": "585",
    "juz": "30",
    "hizb": "59.25",
    "asbab": "0",
    "audio": "https://cdn.alquran.cloud/media/audio/ayah/ar.alafasy/5780",
    "theme": null,
    "text": "Kemudian, jika menghendaki, Dia membangkitkannya kembali.",
    "notes": null,
    "audio_partial": "{\"01\":\"https://cdn.equran.id/audio-partial/Abdullah-Al-Juhany/080022.mp3\",\"02\":\"https://cdn.equran.id/audio-partial/Abdul-Muhsin-Al-Qasim/080022.mp3\",\"03\":\"https://cdn.equran.id/audio-partial/Abdurrahman-as-Sudais/080022.mp3\",\"04\":\"https://cdn.equran.id/audio-partial/Ibrahim-Al-Dossari/080022.mp3\",\"05\":\"https://cdn.equran.id/audio-partial/Misyari-Rasyid-Al-Afasi/080022.mp3\",\"06\":\"https://cdn.equran.id/audio-partial/Yasser-Al-Dosari/080022.mp3\"}"
  },
  {
    "id": "5781",
    "surah": "80",
    "ayah": "23",
    "arab": "كَلَّا لَمَّا يَقْضِ مَآ اَمَرَهٗۗ",
    "latin": "Kallā lammā yaqḍi mā amarah(ū).",
    "page": "585",
    "juz": "30",
    "hizb": "59.25",
    "asbab": "0",
    "audio": "https://cdn.alquran.cloud/media/audio/ayah/ar.alafasy/5781",
    "theme": null,
    "text": "Sekali-kali jangan (begitu)! Dia (manusia) itu belum melaksanakan apa yang Dia (Allah) perintahkan kepadanya.",
    "notes": null,
    "audio_partial": "{\"01\":\"https://cdn.equran.id/audio-partial/Abdullah-Al-Juhany/080023.mp3\",\"02\":\"https://cdn.equran.id/audio-partial/Abdul-Muhsin-Al-Qasim/080023.mp3\",\"03\":\"https://cdn.equran.id/audio-partial/Abdurrahman-as-Sudais/080023.mp3\",\"04\":\"https://cdn.equran.id/audio-partial/Ibrahim-Al-Dossari/080023.mp3\",\"05\":\"https://cdn.equran.id/audio-partial/Misyari-Rasyid-Al-Afasi/080023.mp3\",\"06\":\"https://cdn.equran.id/audio-partial/Yasser-Al-Dosari/080023.mp3\"}"
  },
  {
    "id": "5782",
    "surah": "80",
    "ayah": "24",
    "arab": "فَلْيَنْظُرِ الْاِنْسَانُ اِلٰى طَعَامِهٖٓ ۙ",
    "latin": "Falyanẓuril-insānu ilā ṭa‘āmih(ī).",
    "page": "585",
    "juz": "30",
    "hizb": "59.25",
    "asbab": "0",
    "audio": "https://cdn.alquran.cloud/media/audio/ayah/ar.alafasy/5782",
    "theme": null,
    "text": "Maka, hendaklah manusia itu memperhatikan makanannya.",
    "notes": null,
    "audio_partial": "{\"01\":\"https://cdn.equran.id/audio-partial/Abdullah-Al-Juhany/080024.mp3\",\"02\":\"https://cdn.equran.id/audio-partial/Abdul-Muhsin-Al-Qasim/080024.mp3\",\"03\":\"https://cdn.equran.id/audio-partial/Abdurrahman-as-Sudais/080024.mp3\",\"04\":\"https://cdn.equran.id/audio-partial/Ibrahim-Al-Dossari/080024.mp3\",\"05\":\"https://cdn.equran.id/audio-partial/Misyari-Rasyid-Al-Afasi/080024.mp3\",\"06\":\"https://cdn.equran.id/audio-partial/Yasser-Al-Dosari/080024.mp3\"}"
  },
  {
    "id": "5783",
    "surah": "80",
    "ayah": "25",
    "arab": "اَنَّا صَبَبْنَا الْمَاۤءَ صَبًّاۙ",
    "latin": "Annā ṣababnal-mā'a ṣabbā(n).",
    "page": "585",
    "juz": "30",
    "hizb": "59.25",
    "asbab": "0",
    "audio": "https://cdn.alquran.cloud/media/audio/ayah/ar.alafasy/5783",
    "theme": null,
    "text": "Sesungguhnya Kami telah mencurahkan air (dari langit) dengan berlimpah.",
    "notes": null,
    "audio_partial": "{\"01\":\"https://cdn.equran.id/audio-partial/Abdullah-Al-Juhany/080025.mp3\",\"02\":\"https://cdn.equran.id/audio-partial/Abdul-Muhsin-Al-Qasim/080025.mp3\",\"03\":\"https://cdn.equran.id/audio-partial/Abdurrahman-as-Sudais/080025.mp3\",\"04\":\"https://cdn.equran.id/audio-partial/Ibrahim-Al-Dossari/080025.mp3\",\"05\":\"https://cdn.equran.id/audio-partial/Misyari-Rasyid-Al-Afasi/080025.mp3\",\"06\":\"https://cdn.equran.id/audio-partial/Yasser-Al-Dosari/080025.mp3\"}"
  },
  {
    "id": "5784",
    "surah": "80",
    "ayah": "26",
    "arab": "ثُمَّ شَقَقْنَا الْاَرْضَ شَقًّاۙ",
    "latin": "Ṡumma syaqaqnal-arḍa syaqqā(n).",
    "page": "585",
    "juz": "30",
    "hizb": "59.25",
    "asbab": "0",
    "audio": "https://cdn.alquran.cloud/media/audio/ayah/ar.alafasy/5784",
    "theme": null,
    "text": "Kemudian, Kami belah bumi dengan sebaik-baiknya.",
    "notes": null,
    "audio_partial": "{\"01\":\"https://cdn.equran.id/audio-partial/Abdullah-Al-Juhany/080026.mp3\",\"02\":\"https://cdn.equran.id/audio-partial/Abdul-Muhsin-Al-Qasim/080026.mp3\",\"03\":\"https://cdn.equran.id/audio-partial/Abdurrahman-as-Sudais/080026.mp3\",\"04\":\"https://cdn.equran.id/audio-partial/Ibrahim-Al-Dossari/080026.mp3\",\"05\":\"https://cdn.equran.id/audio-partial/Misyari-Rasyid-Al-Afasi/080026.mp3\",\"06\":\"https://cdn.equran.id/audio-partial/Yasser-Al-Dosari/080026.mp3\"}"
  },
  {
    "id": "5785",
    "surah": "80",
    "ayah": "27",
    "arab": "فَاَنْۢبَتْنَا فِيْهَا حَبًّاۙ",
    "latin": "Fa'ambatnā fīhā ḥabbā(n).",
    "page": "585",
    "juz": "30",
    "hizb": "59.25",
    "asbab": "0",
    "audio": "https://cdn.alquran.cloud/media/audio/ayah/ar.alafasy/5785",
    "theme": null,
    "text": "Lalu, Kami tumbuhkan padanya biji-bijian,",
    "notes": null,
    "audio_partial": "{\"01\":\"https://cdn.equran.id/audio-partial/Abdullah-Al-Juhany/080027.mp3\",\"02\":\"https://cdn.equran.id/audio-partial/Abdul-Muhsin-Al-Qasim/080027.mp3\",\"03\":\"https://cdn.equran.id/audio-partial/Abdurrahman-as-Sudais/080027.mp3\",\"04\":\"https://cdn.equran.id/audio-partial/Ibrahim-Al-Dossari/080027.mp3\",\"05\":\"https://cdn.equran.id/audio-partial/Misyari-Rasyid-Al-Afasi/080027.mp3\",\"06\":\"https://cdn.equran.id/audio-partial/Yasser-Al-Dosari/080027.mp3\"}"
  },
  {
    "id": "5786",
    "surah": "80",
    "ayah": "28",
    "arab": "وَّعِنَبًا وَّقَضْبًاۙ",
    "latin": "Wa ‘inabaw wa qaḍbā(n).",
    "page": "585",
    "juz": "30",
    "hizb": "59.25",
    "asbab": "0",
    "audio": "https://cdn.alquran.cloud/media/audio/ayah/ar.alafasy/5786",
    "theme": null,
    "text": "anggur, sayur-sayuran,",
    "notes": null,
    "audio_partial": "{\"01\":\"https://cdn.equran.id/audio-partial/Abdullah-Al-Juhany/080028.mp3\",\"02\":\"https://cdn.equran.id/audio-partial/Abdul-Muhsin-Al-Qasim/080028.mp3\",\"03\":\"https://cdn.equran.id/audio-partial/Abdurrahman-as-Sudais/080028.mp3\",\"04\":\"https://cdn.equran.id/audio-partial/Ibrahim-Al-Dossari/080028.mp3\",\"05\":\"https://cdn.equran.id/audio-partial/Misyari-Rasyid-Al-Afasi/080028.mp3\",\"06\":\"https://cdn.equran.id/audio-partial/Yasser-Al-Dosari/080028.mp3\"}"
  },
  {
    "id": "5787",
    "surah": "80",
    "ayah": "29",
    "arab": "وَّزَيْتُوْنًا وَّنَخْلًاۙ",
    "latin": "Wa zaitūnaw wa nakhlā(n).",
    "page": "585",
    "juz": "30",
    "hizb": "59.25",
    "asbab": "0",
    "audio": "https://cdn.alquran.cloud/media/audio/ayah/ar.alafasy/5787",
    "theme": null,
    "text": "zaitun, pohon kurma,",
    "notes": null,
    "audio_partial": "{\"01\":\"https://cdn.equran.id/audio-partial/Abdullah-Al-Juhany/080029.mp3\",\"02\":\"https://cdn.equran.id/audio-partial/Abdul-Muhsin-Al-Qasim/080029.mp3\",\"03\":\"https://cdn.equran.id/audio-partial/Abdurrahman-as-Sudais/080029.mp3\",\"04\":\"https://cdn.equran.id/audio-partial/Ibrahim-Al-Dossari/080029.mp3\",\"05\":\"https://cdn.equran.id/audio-partial/Misyari-Rasyid-Al-Afasi/080029.mp3\",\"06\":\"https://cdn.equran.id/audio-partial/Yasser-Al-Dosari/080029.mp3\"}"
  },
  {
    "id": "5788",
    "surah": "80",
    "ayah": "30",
    "arab": "وَّحَدَاۤىِٕقَ غُلْبًا",
    "latin": "Wa ḥadā'iqa gulbā(n).",
    "page": "585",
    "juz": "30",
    "hizb": "59.25",
    "asbab": "0",
    "audio": "https://cdn.alquran.cloud/media/audio/ayah/ar.alafasy/5788",
    "theme": null,
    "text": "kebun-kebun (yang) rindang,",
    "notes": null,
    "audio_partial": "{\"01\":\"https://cdn.equran.id/audio-partial/Abdullah-Al-Juhany/080030.mp3\",\"02\":\"https://cdn.equran.id/audio-partial/Abdul-Muhsin-Al-Qasim/080030.mp3\",\"03\":\"https://cdn.equran.id/audio-partial/Abdurrahman-as-Sudais/080030.mp3\",\"04\":\"https://cdn.equran.id/audio-partial/Ibrahim-Al-Dossari/080030.mp3\",\"05\":\"https://cdn.equran.id/audio-partial/Misyari-Rasyid-Al-Afasi/080030.mp3\",\"06\":\"https://cdn.equran.id/audio-partial/Yasser-Al-Dosari/080030.mp3\"}"
  },
  {
    "id": "5789",
    "surah": "80",
    "ayah": "31",
    "arab": "وَفَاكِهَةً وَّاَبًّا",
    "latin": "Wa fākihataw wa abbā(n).",
    "page": "585",
    "juz": "30",
    "hizb": "59.25",
    "asbab": "0",
    "audio": "https://cdn.alquran.cloud/media/audio/ayah/ar.alafasy/5789",
    "theme": null,
    "text": "buah-buahan, dan rerumputan.",
    "notes": null,
    "audio_partial": "{\"01\":\"https://cdn.equran.id/audio-partial/Abdullah-Al-Juhany/080031.mp3\",\"02\":\"https://cdn.equran.id/audio-partial/Abdul-Muhsin-Al-Qasim/080031.mp3\",\"03\":\"https://cdn.equran.id/audio-partial/Abdurrahman-as-Sudais/080031.mp3\",\"04\":\"https://cdn.equran.id/audio-partial/Ibrahim-Al-Dossari/080031.mp3\",\"05\":\"https://cdn.equran.id/audio-partial/Misyari-Rasyid-Al-Afasi/080031.mp3\",\"06\":\"https://cdn.equran.id/audio-partial/Yasser-Al-Dosari/080031.mp3\"}"
  },
  {
    "id": "5790",
    "surah": "80",
    "ayah": "32",
    "arab": "مَتَاعًا لَّكُمْ وَلِاَنْعَامِكُمْۗ",
    "latin": "Matā‘al lakum wa li'an‘āmikum.",
    "page": "585",
    "juz": "30",
    "hizb": "59.25",
    "asbab": "0",
    "audio": "https://cdn.alquran.cloud/media/audio/ayah/ar.alafasy/5790",
    "theme": null,
    "text": "(Semua itu disediakan) untuk kesenanganmu dan hewan-hewan ternakmu.",
    "notes": null,
    "audio_partial": "{\"01\":\"https://cdn.equran.id/audio-partial/Abdullah-Al-Juhany/080032.mp3\",\"02\":\"https://cdn.equran.id/audio-partial/Abdul-Muhsin-Al-Qasim/080032.mp3\",\"03\":\"https://cdn.equran.id/audio-partial/Abdurrahman-as-Sudais/080032.mp3\",\"04\":\"https://cdn.equran.id/audio-partial/Ibrahim-Al-Dossari/080032.mp3\",\"05\":\"https://cdn.equran.id/audio-partial/Misyari-Rasyid-Al-Afasi/080032.mp3\",\"06\":\"https://cdn.equran.id/audio-partial/Yasser-Al-Dosari/080032.mp3\"}"
  },
  {
    "id": "5791",
    "surah": "80",
    "ayah": "33",
    "arab": "فَاِذَا جَاۤءَتِ الصَّاۤخَّةُ ۖ",
    "latin": "Fa iżā jā'atiṣ-ṣākhkhah(tu).",
    "page": "585",
    "juz": "30",
    "hizb": "59.25",
    "asbab": "0",
    "audio": "https://cdn.alquran.cloud/media/audio/ayah/ar.alafasy/5791",
    "theme": null,
    "text": "Maka, apabila datang suara yang memekakkan (dari tiupan sangkakala),",
    "notes": null,
    "audio_partial": "{\"01\":\"https://cdn.equran.id/audio-partial/Abdullah-Al-Juhany/080033.mp3\",\"02\":\"https://cdn.equran.id/audio-partial/Abdul-Muhsin-Al-Qasim/080033.mp3\",\"03\":\"https://cdn.equran.id/audio-partial/Abdurrahman-as-Sudais/080033.mp3\",\"04\":\"https://cdn.equran.id/audio-partial/Ibrahim-Al-Dossari/080033.mp3\",\"05\":\"https://cdn.equran.id/audio-partial/Misyari-Rasyid-Al-Afasi/080033.mp3\",\"06\":\"https://cdn.equran.id/audio-partial/Yasser-Al-Dosari/080033.mp3\"}"
  },
  {
    "id": "5792",
    "surah": "80",
    "ayah": "34",
    "arab": "يَوْمَ يَفِرُّ الْمَرْءُ مِنْ اَخِيْهِۙ",
    "latin": "Yauma yafirrul-mar'u min akhīh(i).",
    "page": "585",
    "juz": "30",
    "hizb": "59.25",
    "asbab": "0",
    "audio": "https://cdn.alquran.cloud/media/audio/ayah/ar.alafasy/5792",
    "theme": null,
    "text": "pada hari itu manusia lari dari saudaranya,",
    "notes": null,
    "audio_partial": "{\"01\":\"https://cdn.equran.id/audio-partial/Abdullah-Al-Juhany/080034.mp3\",\"02\":\"https://cdn.equran.id/audio-partial/Abdul-Muhsin-Al-Qasim/080034.mp3\",\"03\":\"https://cdn.equran.id/audio-partial/Abdurrahman-as-Sudais/080034.mp3\",\"04\":\"https://cdn.equran.id/audio-partial/Ibrahim-Al-Dossari/080034.mp3\",\"05\":\"https://cdn.equran.id/audio-partial/Misyari-Rasyid-Al-Afasi/080034.mp3\",\"06\":\"https://cdn.equran.id/audio-partial/Yasser-Al-Dosari/080034.mp3\"}"
  },
  {
    "id": "5793",
    "surah": "80",
    "ayah": "35",
    "arab": "وَاُمِّهٖ وَاَبِيْهِۙ",
    "latin": "Wa ummihī wa abīh(i).",
    "page": "585",
    "juz": "30",
    "hizb": "59.25",
    "asbab": "0",
    "audio": "https://cdn.alquran.cloud/media/audio/ayah/ar.alafasy/5793",
    "theme": null,
    "text": "(dari) ibu dan bapaknya,",
    "notes": null,
    "audio_partial": "{\"01\":\"https://cdn.equran.id/audio-partial/Abdullah-Al-Juhany/080035.mp3\",\"02\":\"https://cdn.equran.id/audio-partial/Abdul-Muhsin-Al-Qasim/080035.mp3\",\"03\":\"https://cdn.equran.id/audio-partial/Abdurrahman-as-Sudais/080035.mp3\",\"04\":\"https://cdn.equran.id/audio-partial/Ibrahim-Al-Dossari/080035.mp3\",\"05\":\"https://cdn.equran.id/audio-partial/Misyari-Rasyid-Al-Afasi/080035.mp3\",\"06\":\"https://cdn.equran.id/audio-partial/Yasser-Al-Dosari/080035.mp3\"}"
  },
  {
    "id": "5794",
    "surah": "80",
    "ayah": "36",
    "arab": "وَصَاحِبَتِهٖ وَبَنِيْهِۗ",
    "latin": "Wa ṣāḥibatihī wa banīh(i).",
    "page": "585",
    "juz": "30",
    "hizb": "59.25",
    "asbab": "0",
    "audio": "https://cdn.alquran.cloud/media/audio/ayah/ar.alafasy/5794",
    "theme": null,
    "text": "serta (dari) istri dan anak-anaknya.",
    "notes": null,
    "audio_partial": "{\"01\":\"https://cdn.equran.id/audio-partial/Abdullah-Al-Juhany/080036.mp3\",\"02\":\"https://cdn.equran.id/audio-partial/Abdul-Muhsin-Al-Qasim/080036.mp3\",\"03\":\"https://cdn.equran.id/audio-partial/Abdurrahman-as-Sudais/080036.mp3\",\"04\":\"https://cdn.equran.id/audio-partial/Ibrahim-Al-Dossari/080036.mp3\",\"05\":\"https://cdn.equran.id/audio-partial/Misyari-Rasyid-Al-Afasi/080036.mp3\",\"06\":\"https://cdn.equran.id/audio-partial/Yasser-Al-Dosari/080036.mp3\"}"
  },
  {
    "id": "5795",
    "surah": "80",
    "ayah": "37",
    "arab": "لِكُلِّ امْرِئٍ مِّنْهُمْ يَوْمَىِٕذٍ شَأْنٌ يُّغْنِيْهِۗ",
    "latin": "Likullimri'im minhum yauma'iżin sya'nuy yugnīh(i).",
    "page": "585",
    "juz": "30",
    "hizb": "59.25",
    "asbab": "0",
    "audio": "https://cdn.alquran.cloud/media/audio/ayah/ar.alafasy/5795",
    "theme": null,
    "text": "Setiap orang dari mereka pada hari itu mempunyai urusan yang menyibukkannya.",
    "notes": null,
    "audio_partial": "{\"01\":\"https://cdn.equran.id/audio-partial/Abdullah-Al-Juhany/080037.mp3\",\"02\":\"https://cdn.equran.id/audio-partial/Abdul-Muhsin-Al-Qasim/080037.mp3\",\"03\":\"https://cdn.equran.id/audio-partial/Abdurrahman-as-Sudais/080037.mp3\",\"04\":\"https://cdn.equran.id/audio-partial/Ibrahim-Al-Dossari/080037.mp3\",\"05\":\"https://cdn.equran.id/audio-partial/Misyari-Rasyid-Al-Afasi/080037.mp3\",\"06\":\"https://cdn.equran.id/audio-partial/Yasser-Al-Dosari/080037.mp3\"}"
  },
  {
    "id": "5796",
    "surah": "80",
    "ayah": "38",
    "arab": "وُجُوْهٌ يَّوْمَىِٕذٍ مُّسْفِرَةٌۙ",
    "latin": "Wujūhuy yauma'iżim musfirah(tun).",
    "page": "585",
    "juz": "30",
    "hizb": "59.25",
    "asbab": "0",
    "audio": "https://cdn.alquran.cloud/media/audio/ayah/ar.alafasy/5796",
    "theme": null,
    "text": "Pada hari itu ada wajah-wajah yang berseri-seri,",
    "notes": null,
    "audio_partial": "{\"01\":\"https://cdn.equran.id/audio-partial/Abdullah-Al-Juhany/080038.mp3\",\"02\":\"https://cdn.equran.id/audio-partial/Abdul-Muhsin-Al-Qasim/080038.mp3\",\"03\":\"https://cdn.equran.id/audio-partial/Abdurrahman-as-Sudais/080038.mp3\",\"04\":\"https://cdn.equran.id/audio-partial/Ibrahim-Al-Dossari/080038.mp3\",\"05\":\"https://cdn.equran.id/audio-partial/Misyari-Rasyid-Al-Afasi/080038.mp3\",\"06\":\"https://cdn.equran.id/audio-partial/Yasser-Al-Dosari/080038.mp3\"}"
  },
  {
    "id": "5797",
    "surah": "80",
    "ayah": "39",
    "arab": "ضَاحِكَةٌ مُّسْتَبْشِرَةٌ ۚ",
    "latin": "Ḍāḥikatum mustabsyirah(tun).",
    "page": "585",
    "juz": "30",
    "hizb": "59.25",
    "asbab": "0",
    "audio": "https://cdn.alquran.cloud/media/audio/ayah/ar.alafasy/5797",
    "theme": null,
    "text": "tertawa lagi gembira ria.",
    "notes": null,
    "audio_partial": "{\"01\":\"https://cdn.equran.id/audio-partial/Abdullah-Al-Juhany/080039.mp3\",\"02\":\"https://cdn.equran.id/audio-partial/Abdul-Muhsin-Al-Qasim/080039.mp3\",\"03\":\"https://cdn.equran.id/audio-partial/Abdurrahman-as-Sudais/080039.mp3\",\"04\":\"https://cdn.equran.id/audio-partial/Ibrahim-Al-Dossari/080039.mp3\",\"05\":\"https://cdn.equran.id/audio-partial/Misyari-Rasyid-Al-Afasi/080039.mp3\",\"06\":\"https://cdn.equran.id/audio-partial/Yasser-Al-Dosari/080039.mp3\"}"
  },
  {
    "id": "5798",
    "surah": "80",
    "ayah": "40",
    "arab": "وَوُجُوْهٌ يَّوْمَىِٕذٍ عَلَيْهَا غَبَرَةٌۙ",
    "latin": "Wa wujūhuy yauma'iżin ‘alaihā gabarah(tun).",
    "page": "585",
    "juz": "30",
    "hizb": "59.25",
    "asbab": "0",
    "audio": "https://cdn.alquran.cloud/media/audio/ayah/ar.alafasy/5798",
    "theme": null,
    "text": "Pada hari itu ada (pula) wajah-wajah yang tertutup debu (suram)",
    "notes": null,
    "audio_partial": "{\"01\":\"https://cdn.equran.id/audio-partial/Abdullah-Al-Juhany/080040.mp3\",\"02\":\"https://cdn.equran.id/audio-partial/Abdul-Muhsin-Al-Qasim/080040.mp3\",\"03\":\"https://cdn.equran.id/audio-partial/Abdurrahman-as-Sudais/080040.mp3\",\"04\":\"https://cdn.equran.id/audio-partial/Ibrahim-Al-Dossari/080040.mp3\",\"05\":\"https://cdn.equran.id/audio-partial/Misyari-Rasyid-Al-Afasi/080040.mp3\",\"06\":\"https://cdn.equran.id/audio-partial/Yasser-Al-Dosari/080040.mp3\"}"
  },
  {
    "id": "5799",
    "surah": "80",
    "ayah": "41",
    "arab": "تَرْهَقُهَا قَتَرَةٌ ۗ",
    "latin": "Tarhaquhā qatarah(tun).",
    "page": "585",
    "juz": "30",
    "hizb": "59.25",
    "asbab": "0",
    "audio": "https://cdn.alquran.cloud/media/audio/ayah/ar.alafasy/5799",
    "theme": null,
    "text": "dan tertutup oleh kegelapan (ditimpa kehinaan dan kesusahan).",
    "notes": null,
    "audio_partial": "{\"01\":\"https://cdn.equran.id/audio-partial/Abdullah-Al-Juhany/080041.mp3\",\"02\":\"https://cdn.equran.id/audio-partial/Abdul-Muhsin-Al-Qasim/080041.mp3\",\"03\":\"https://cdn.equran.id/audio-partial/Abdurrahman-as-Sudais/080041.mp3\",\"04\":\"https://cdn.equran.id/audio-partial/Ibrahim-Al-Dossari/080041.mp3\",\"05\":\"https://cdn.equran.id/audio-partial/Misyari-Rasyid-Al-Afasi/080041.mp3\",\"06\":\"https://cdn.equran.id/audio-partial/Yasser-Al-Dosari/080041.mp3\"}"
  },
  {
    "id": "5800",
    "surah": "80",
    "ayah": "42",
    "arab": "اُولٰۤىِٕكَ هُمُ الْكَفَرَةُ الْفَجَرَةُ ࣖ",
    "latin": "Ulā'ika humul-kafaratul-fajarah(tu).",
    "page": "585",
    "juz": "30",
    "hizb": "59.25",
    "asbab": "0",
    "audio": "https://cdn.alquran.cloud/media/audio/ayah/ar.alafasy/5800",
    "theme": null,
    "text": "Mereka itulah orang-orang kafir lagi para pendurhaka.",
    "notes": null,
    "audio_partial": "{\"01\":\"https://cdn.equran.id/audio-partial/Abdullah-Al-Juhany/080042.mp3\",\"02\":\"https://cdn.equran.id/audio-partial/Abdul-Muhsin-Al-Qasim/080042.mp3\",\"03\":\"https://cdn.equran.id/audio-partial/Abdurrahman-as-Sudais/080042.mp3\",\"04\":\"https://cdn.equran.id/audio-partial/Ibrahim-Al-Dossari/080042.mp3\",\"05\":\"https://cdn.equran.id/audio-partial/Misyari-Rasyid-Al-Afasi/080042.mp3\",\"06\":\"https://cdn.equran.id/audio-partial/Yasser-Al-Dosari/080042.mp3\"}"
  }
]